vip_client/__init__.py
vip_client/classes/VipGirder.py
vip_client/classes/VipLauncher.py
vip_client/classes/VipSession.py
vip_client/classes/__init__.py
vip_client/utils/__init__.py
vip_client/utils/vip.py
vip_client-0.1.9.dist-info/METADATA
vip_client-0.1.9.dist-info/WHEEL
vip_client-0.1.9.dist-info/licenses/LICENSE.txt
vip_client-0.1.9.dist-info/RECORD
