Metadata-Version: 2.4
Name: vip-client
Version: 0.1.9
Summary: Python client to use the Virtual Imaging Platform (VIP) through its RESTful API.
Project-URL: Homepage, https://vip.creatis.insa-lyon.fr
Project-URL: Source, https://github.com/virtual-imaging-platform/VIP-python-client
Project-URL: Tracker, https://github.com/virtual-imaging-platform/VIP-python-client/issues
Author-email: Gaël Vila <gael.vila@creatis.insa-lyon.fr>
Maintainer-email: Gaël Vila <gael.vila@creatis.insa-lyon.fr>, Axel Bonnet <axel.bonnet@creatis.insa-lyon.fr>
License-File: LICENSE.txt
Classifier: Development Status :: 3 - Alpha
Classifier: Intended Audience :: Education
Classifier: Intended Audience :: Science/Research
Classifier: License :: CeCILL-B Free Software License Agreement (CECILL-B)
Classifier: Natural Language :: English
Classifier: Operating System :: OS Independent
Classifier: Programming Language :: Python :: 3 :: Only
Classifier: Topic :: Scientific/Engineering :: Image Processing
Classifier: Topic :: Scientific/Engineering :: Medical Science Apps.
Requires-Python: >=3.7
Requires-Dist: girder-client
Requires-Dist: requests
